pysyncdroid/__init__.py
pysyncdroid/cli.py
pysyncdroid/exceptions.py
pysyncdroid/find_device.py
pysyncdroid/gvfs.py
pysyncdroid/sync.py
pysyncdroid/utils.py
tests/__init__.py
tests/test_cli.py
tests/test_find_device.py
tests/test_gvfs.py
tests/test_sync.py
tests/test_sync_integration.py
tests/test_utils.py
pysyncdroid-1.1.0.dist-info/LICENSE
pysyncdroid-1.1.0.dist-info/METADATA
pysyncdroid-1.1.0.dist-info/WHEEL
pysyncdroid-1.1.0.dist-info/entry_points.txt
pysyncdroid-1.1.0.dist-info/top_level.txt
pysyncdroid-1.1.0.dist-info/RECORD
